pyroll/lendl_equivalent_method/__init__.py
pyroll/lendl_equivalent_method/lendl_method.py
pyroll/lendl_equivalent_method/report.py
pyroll_lendl_equivalent_method-3.0.0.post0.dist-info/METADATA
pyroll_lendl_equivalent_method-3.0.0.post0.dist-info/WHEEL
pyroll_lendl_equivalent_method-3.0.0.post0.dist-info/licenses/LICENSE
pyroll_lendl_equivalent_method-3.0.0.post0.dist-info/RECORD
