Metadata-Version: 2.3
Name: pyroll-lendl-equivalent-method
Version: 3.0.0.post0
Summary: Plugin for PyRolL providing the equivalent rectangle method by Lendl.
Project-URL: Homepage, https://pyroll-project.github.io
Project-URL: Repository, https://github.com/pyroll-project/pyroll-lendl-equivalent-method
Project-URL: Documentation, https://github.com/pyroll-project/pyroll-lendl-equivalent-method/blob/main/docs/docs.pdf
Author-email: Christoph Renzing <christoph.renzing@imf.tu-freiberg.de>, Max Weiner <max.weiner@imf.tu-freiberg.de>
License-Expression: BSD-3-Clause
License-File: LICENSE
Classifier: Intended Audience :: Manufacturing
Classifier: Intended Audience :: Science/Research
Classifier: Operating System :: OS Independent
Classifier: Topic :: Scientific/Engineering
Requires-Python: <4.0,>=3.9
Requires-Dist: pyroll-core~=3.0
